{
  "$schema": "https://schemas.wp.org/trunk/theme.json",
  "version": 3,
  "title": "Amber CRT",
  "settings": {
    "color": {
      "defaultPalette": false,
      "palette": [
        {
          "name": "Screen",
          "slug": "screen",
          "color": "#000000"
        },
        {
          "name": "Amber",
          "slug": "amber",
          "color": "#ff9900"
        },
        {
          "name": "Dim",
          "slug": "dim",
          "color": "#999999"
        },
        {
          "name": "Panel",
          "slug": "panel",
          "color": "#333333"
        }
      ]
    },
    "spacing": {
      "spacingScale": {
        "operator": "*",
        "increment": 1.5,
        "steps": 4,
        "mediumStep": 1.5,
        "unit": "rem"
      }
    },
    "custom": {
      "dirtbag": {
        "truckIconFilter": "brightness(0) saturate(100%) invert(64%) sepia(85%) saturate(1800%) hue-rotate(360deg) brightness(103%) contrast(105%)"
      }
    }
  },
  "styles": {
    "color": {
      "background": "#000000",
      "text": "#ff9900"
    },
    "elements": {
      "button": {
        "border": {
          "color": "#ff9900",
          "style": "solid",
          "width": "1px",
          "radius": "0"
        },
        "color": {
          "background": "#000000",
          "text": "#ff9900"
        },
        "spacing": {
          "padding": {
            "bottom": "0.5rem",
            "left": "0.75rem",
            "right": "0.75rem",
            "top": "0.5rem"
          }
        }
      },
      "caption": {
        "color": {
          "text": "#999999"
        },
        "typography": {
          "fontSize": "0.875rem"
        }
      },
      "link": {
        "color": {
          "text": "#ff9900"
        }
      }
    },
    "spacing": {
      "blockGap": "1rem",
      "padding": {
        "bottom": "2rem",
        "left": "1rem",
        "right": "1rem",
        "top": "2rem"
      }
    },
    "typography": {
      "fontFamily": "'Courier New', Courier, monospace"
    }
  }
}
